aiida_vasp/__init__.py
aiida_vasp/assistant/__init__.py
aiida_vasp/assistant/parameters.py
aiida_vasp/assistant/parameters.yml
aiida_vasp/calcs/__init__.py
aiida_vasp/calcs/base.py
aiida_vasp/calcs/immigrant.py
aiida_vasp/calcs/monitors.py
aiida_vasp/calcs/neb.py
aiida_vasp/calcs/vasp.py
aiida_vasp/calcs/vasp2w90.py
aiida_vasp/calcs/w90win.py
aiida_vasp/commands/__init__.py
aiida_vasp/commands/dryrun_vasp.py
aiida_vasp/commands/immigrant.py
aiida_vasp/commands/launch.py
aiida_vasp/commands/mock_vasp.py
aiida_vasp/commands/option_parser.py
aiida_vasp/commands/options.py
aiida_vasp/commands/potcar.py
aiida_vasp/commands/tools.py
aiida_vasp/commands/utils.py
aiida_vasp/common/VaspPreset.yaml
aiida_vasp/common/__init__.py
aiida_vasp/common/builder_updater.py
aiida_vasp/common/dryrun.py
aiida_vasp/common/magmapping.py
aiida_vasp/common/sumo_kpath.py
aiida_vasp/common/transform.py
aiida_vasp/data/__init__.py
aiida_vasp/data/archive.py
aiida_vasp/data/chargedensity.py
aiida_vasp/data/potcar.py
aiida_vasp/data/potpaw_sha512.json
aiida_vasp/data/wavefun.py
aiida_vasp/inputset/MITRelaxSet.yaml
aiida_vasp/inputset/UCLPhononSet.yaml
aiida_vasp/inputset/UCLRelaxSet.yaml
aiida_vasp/inputset/__init__.py
aiida_vasp/inputset/base.py
aiida_vasp/inputset/pmgset.py
aiida_vasp/inputset/vaspsets.py
aiida_vasp/parsers/__init__.py
aiida_vasp/parsers/neb.py
aiida_vasp/parsers/vasp.py
aiida_vasp/parsers/content_parsers/__init__.py
aiida_vasp/parsers/content_parsers/base.py
aiida_vasp/parsers/content_parsers/chgcar.py
aiida_vasp/parsers/content_parsers/doscar.py
aiida_vasp/parsers/content_parsers/eigenval.py
aiida_vasp/parsers/content_parsers/incar.py
aiida_vasp/parsers/content_parsers/kpoints.py
aiida_vasp/parsers/content_parsers/outcar.py
aiida_vasp/parsers/content_parsers/poscar.py
aiida_vasp/parsers/content_parsers/potcar.py
aiida_vasp/parsers/content_parsers/stream.py
aiida_vasp/parsers/content_parsers/vasprun.py
aiida_vasp/parsers/content_parsers/win.py
aiida_vasp/protocols/__init__.py
aiida_vasp-5.0.0.dist-info/entry_points.txt
aiida_vasp-5.0.0.dist-info/licenses/LICENSE.txt
aiida_vasp-5.0.0.dist-info/WHEEL
aiida_vasp-5.0.0.dist-info/METADATA
aiida_vasp-5.0.0.dist-info/RECORD
