Metadata-Version: 2.4
Name: aiida-vasp
Version: 5.0.0
Summary: AiiDA plugin for running VASP calculations and workflows.
Keywords: aiida,plugin
Author-email: Espen Flage-Larsen <espen.flage-larsen@sigma2.no>
Requires-Python: >=3.10
Classifier: Programming Language :: Python
Classifier: Intended Audience :: Science/Research
Classifier: Natural Language :: English
Classifier: Framework :: AiiDA
Classifier: Development Status :: 5 - Production/Stable
Classifier: Environment :: Plugins
Classifier: Intended Audience :: Science/Research
Classifier: License :: OSI Approved :: MIT License
Classifier: Programming Language :: Python :: 3.10
Classifier: Programming Language :: Python :: 3.11
Classifier: Programming Language :: Python :: 3.12
Classifier: Topic :: Scientific/Engineering :: Physics
Classifier: Topic :: Scientific/Engineering :: Chemistry
Classifier: Framework :: AiiDA
License-File: LICENSE.txt
Requires-Dist: aiida-core>=2.3
Requires-Dist: ase
Requires-Dist: lxml
Requires-Dist: seekpath
Requires-Dist: packaging
Requires-Dist: pydantic
Requires-Dist: parsevasp>=3.4
Requires-Dist: spglib
Requires-Dist: pyyaml
Requires-Dist: aiida-core[docs]~=2.4 ; extra == "docs"
Requires-Dist: sphinx-autodoc2 ; extra == "docs"
Requires-Dist: sphinx-autobuild ; extra == "docs"
Requires-Dist: sphinx-lint ; extra == "docs"
Requires-Dist: sphinx-rtd-theme ; extra == "docs"
Requires-Dist: sphinx-click ; extra == "docs"
Requires-Dist: sphinx_copybutton ; extra == "docs"
Requires-Dist: sphinx_design ; extra == "docs"
Requires-Dist: sphinx_togglebutton ; extra == "docs"
Requires-Dist: sphinxext.remoteliteralinclude ; extra == "docs"
Requires-Dist: matplotlib ; extra == "docs"
Requires-Dist: pymatgen ; extra == "docs"
Requires-Dist: matplotlib ; extra == "graphs"
Requires-Dist: pre-commit ; extra == "pre-commit"
Requires-Dist: aiida-core>=2.6 ; extra == "tests"
Requires-Dist: pytest ; extra == "tests"
Requires-Dist: PyCifRW ; extra == "tests"
Requires-Dist: pymatgen ; extra == "tests"
Project-URL: Source, https://github.com/aiida-vasp/aiida-vasp
Provides-Extra: docs
Provides-Extra: graphs
Provides-Extra: pre-commit
Provides-Extra: tests
